CHANGES.txt
LICENSE.txt
MANIFEST.in
README.rst
TODO.txt
setup.py
.hg/last-message.txt
.ve/Lib/no-global-site-packages.txt
.ve/Lib/orig-prefix.txt
.ve/Lib/site-packages/nose-1.1.2-py2.7.egg/EGG-INFO/SOURCES.txt
.ve/Lib/site-packages/nose-1.1.2-py2.7.egg/EGG-INFO/dependency_links.txt
.ve/Lib/site-packages/nose-1.1.2-py2.7.egg/EGG-INFO/entry_points.txt
.ve/Lib/site-packages/nose-1.1.2-py2.7.egg/EGG-INFO/top_level.txt
.ve/Lib/site-packages/nose-1.1.2-py2.7.egg/nose/usage.txt
.ve/Lib/site-packages/pip-1.0.2-py2.7.egg/EGG-INFO/SOURCES.txt
.ve/Lib/site-packages/pip-1.0.2-py2.7.egg/EGG-INFO/dependency_links.txt
.ve/Lib/site-packages/pip-1.0.2-py2.7.egg/EGG-INFO/entry_points.txt
.ve/Lib/site-packages/pip-1.0.2-py2.7.egg/EGG-INFO/top_level.txt
src/specit.py
src/specit.egg-info/PKG-INFO
src/specit.egg-info/SOURCES.txt
src/specit.egg-info/dependency_links.txt
src/specit.egg-info/entry_points.txt
src/specit.egg-info/not-zip-safe
src/specit.egg-info/requires.txt
src/specit.egg-info/top_level.txt