Metadata-Version: 1.0
Name: specit
Version: 0.2.1z
Summary: Create and run executable specifications with Pythonic BDD style grammar
Home-page: https://bitbucket.org/rudylattae/specit
Author: Rudy Lattae
Author-email: rudylattae@gmail.com
License: Simplified BSD
Keywords: Specification,BDD,TDD
Platform: UNKNOWN
Classifier: Development Status :: 7 - Inactive
Classifier: Environment :: Console
Classifier: Intended Audience :: Developers
Classifier: License :: OSI Approved :: BSD License
Classifier: Operating System :: Microsoft :: Windows
Classifier: Programming Language :: Python
Classifier: Programming Language :: Python :: 2.7
